somajo/__init__.py
somajo/alignment.py
somajo/cli.py
somajo/doubly_linked_list.py
somajo/sentence_splitter.py
somajo/somajo.py
somajo/token.py
somajo/tokenizer.py
somajo/utils.py
somajo/data/abbreviations_de.txt
somajo/data/abbreviations_en.txt
somajo/data/camel_case_tokens.txt
somajo/data/eos_abbreviations.txt
somajo/data/non-breaking_hyphenated_words_en.txt
somajo/data/non-breaking_prefixes_en.txt
somajo/data/non-breaking_suffixes_en.txt
somajo/data/single_token_abbreviations_de.txt
somajo/data/single_token_abbreviations_en.txt
somajo/data/single_tokens_de.txt
somajo/data/single_tokens_en.txt
somajo/data/tokens_with_plus_or_ampersand.txt
somajo/data/units.txt
SoMaJo-2.4.3.dist-info/LICENSE.txt
SoMaJo-2.4.3.dist-info/METADATA
SoMaJo-2.4.3.dist-info/WHEEL
SoMaJo-2.4.3.dist-info/entry_points.txt
SoMaJo-2.4.3.dist-info/top_level.txt
SoMaJo-2.4.3.dist-info/RECORD
