Metadata-Version: 2.1
Name: SoMaJo
Version: 2.4.3
Summary: A tokenizer and sentence splitter for German and English web and social media texts.
Author-email: "Thomas Proisl, Peter Uhrig" <thomas.proisl@fau.de>
Maintainer-email: Thomas Proisl <thomas.proisl@fau.de>
License: GNU GENERAL PUBLIC LICENSE
Project-URL: Homepage, https://github.com/tsproisl/SoMaJo
Project-URL: API documentation, https://github.com/tsproisl/SoMaJo/blob/master/doc/build/markdown/somajo.md
Keywords: tokenizer,sentence-splitter
Classifier: Development Status :: 5 - Production/Stable
Classifier: Environment :: Console
Classifier: Intended Audience :: Developers
Classifier: Intended Audience :: Science/Research
Classifier: License :: OSI Approved :: GNU General Public License v3 or later (GPLv3+)
Classifier: Natural Language :: German
Classifier: Natural Language :: English
Classifier: Operating System :: OS Independent
Classifier: Programming Language :: Python :: 3
Classifier: Topic :: Text Processing :: Linguistic
Requires-Python: >=3.8
License-File: LICENSE.txt
Requires-Dist: regex >=2019.02.18
